ngwshare/__init__.py
ngwshare/__init__11.py
ngwshare/constants.py
ngwshare/contract_demo.py
ngwshare/demo.py
ngwshare/funds_demo.py
ngwshare/robot_api.py
ngwshare/robot_api3.py
ngwshare/stock_demo.py
ngwshare/test_api.py
ngwshare/us_demo.py
ngwshare/conn_db/__init__.py
ngwshare/conn_db/conn_mongo.py
ngwshare/conn_db/conn_mysql.py
ngwshare/conn_db/conn_sqlserver.py
ngwshare/data/BXdata.py
ngwshare/data/FactorNew.py
ngwshare/data/HaXin.py
ngwshare/data/NGWTick.py
ngwshare/data/T0Trade.py
ngwshare/data/T1Data.py
ngwshare/data/ZRZQ.py
ngwshare/data/__init__.py
ngwshare/data/contract_extra.py
ngwshare/data/contract_guba.py
ngwshare/data/factor.py
ngwshare/data/statistics_data.py
ngwshare/data/us_data.py
ngwshare/utils/__init__.py
ngwshare/utils/date_util.py
ngwshare/utils/date_utilss.py
ngwshare/utils/freq_util.py
ngwshare/utils/http_util.py
ngwshare/utils/log_util.py
ngwshare/utils/mail_util.py
ngwshare-0.2.6.dist-info/METADATA
ngwshare-0.2.6.dist-info/WHEEL
ngwshare-0.2.6.dist-info/top_level.txt
ngwshare-0.2.6.dist-info/RECORD
