Metadata-Version: 2.1
Name: ngwshare
Version: 0.2.6
Summary: data api 026
Home-page: https://github.com/296348304/ngwshare
Author: Wang Jian
Author-email: 296348304@qq.com
License: UNKNOWN
Platform: UNKNOWN
Classifier: Programming Language :: Python :: 3
Classifier: License :: OSI Approved :: MIT License
Classifier: Operating System :: OS Independent
Requires-Python: >=3.7
